ndim/__init__.py
ndim/cauchy.py
ndim/enr.py
ndim/enr2.py
ndim/nball.py
ndim/ncube.py
ndim/nsimplex.py
ndim/nsphere.py
ndim-0.1.36.dist-info/METADATA
ndim-0.1.36.dist-info/WHEEL
ndim-0.1.36.dist-info/top_level.txt
ndim-0.1.36.dist-info/RECORD
