Metadata-Version: 2.4
Name: ndim
Version: 0.1.36
Summary: Multidimensional volumes and monomial integrals
Author-email: Nico Schlömer <nico.schloemer@gmail.com>
License-Expression: LicenseRef-Proprietary
Project-URL: Homepage, https://github.com/sigma-py/
Project-URL: Issues, https://github.com/sigma-py/ndim/issues
Classifier: Development Status :: 5 - Production/Stable
Classifier: Intended Audience :: Science/Research
Classifier: Operating System :: OS Independent
Classifier: Programming Language :: Python
Classifier: Programming Language :: Python :: 3
Classifier: Programming Language :: Python :: 3.9
Classifier: Programming Language :: Python :: 3.10
Classifier: Programming Language :: Python :: 3.11
Classifier: Programming Language :: Python :: 3.12
Classifier: Programming Language :: Python :: 3.13
Classifier: Topic :: Scientific/Engineering
Classifier: Topic :: Utilities
Requires-Python: >=3.9
Requires-Dist: sympy
Requires-Dist: stonefish-license-manager>=0.5.24
Requires-Dist: x22>=0.2.1
